{
  "cate": "7",
  "date": "10æ21æ¥ 16æ09å",
  "datetime": "2018-10-21T16:09",
  "video": "/news/html/20181021/movie/k10011680041_201810211852_201810211858.html",
  "duration": 66,
  "img": "html/20181021/K10011680041_1810211852_1810211859_01_03.jpg",
  "title": "東京湾アクアラインでマラソン大会 １万7000人が景色楽しむ",
  "summary": "東京湾を横断する東京湾アクアラインを走るマラソン大会が開かれ、およそ１万7000人のランナーが海の上からの景色を楽しみながら走りました。",
  "more": "",
  "body": [
    {
      "title": "",
      "img": "html/20181021/K10011680041_1810211605_1810211609_01_03.jpg",
      "align": "",
      "text": "「ちばアクアラインマラソン」は、千葉県が２年に１度開催し、４回目となることしはマラソンとハーフマラソン、それに車いすのハーフマラソンにおよそ１万7000人が出場しました。<br /><br />千葉県木更津市と川崎市を結ぶ東京湾アクアラインの千葉県側の橋の上を往復する区間がコースの一部となっていて、参加したランナーたちは色とりどりのウェアを身に着け、秋晴れの空の下で、海の上からの景色を楽しみながら走っていました。<br />また、木更津市内のコースの沿道では市民などがランナーに声援を送っていました。<br /><br />名古屋市から参加したという女性は「風がすごく強くて体を持っていかれそうになりましたが、富士山がすごくきれいで、富士山と青い海にパワーをもらいました」と話していました。<br /><br />青森県から来たという51歳の男性は「景色が360度パノラマで、これ以上ない大会でした。途中歩きたくなったけど、沿道からの応援で元気が出ました」と話していました。<br /><br />また、木更津市のスタート地点の周辺では、２年後の東京オリンピック・パラリンピックの「都市ボランティア」を募集している千葉県の担当者がパンフレットを配って、参加者などにボランティアへの応募を呼びかけていました。",
      "textPos": "bottom"
    }
  ],
  "relationNews": [],
  "relationLink": [],
  "word": [
    {
      "link": "word/0000037.html",
      "title": "ロードレース"
    }
  ],
  "news_id": "k10011680041000",
  "yyyy": "2018",
  "mm": "10",
  "dd": "21",
  "url": "https://www3.nhk.or.jp/news/html/20181021/k10011680041000.html?utm_int=news-new_contents_list-items_011"
}