{
  "cate": "1",
  "date": "10æ10æ¥ 14æ25å",
  "datetime": "2018-10-10T14:25",
  "video": "",
  "duration": 0,
  "img": "html/20181010/K10011665771_1810101420_1810101425_01_02.jpg",
  "title": "“卒業後も日本で…”外国人留学生 就職や起業 過去最多に",
  "summary": "日本の大学や専門学校を卒業後、そのまま日本で就職や起業した外国人留学生は、去年１年間で２万2400人余りと、過去最多を更新したことがわかりました。",
  "more": "外国人留学生が大学や専門学校を卒業後、日本で働いたり起業したりするためには、在留資格を「留学」などから就労目的に変更する必要があります。<br /><br />法務省入国管理局によりますと、この在留資格の変更が許可された外国人留学生は去年１年間で２万2419人いて、過去最多だった前の年より2984人増えて、過去最多を更新しました。<br /><br />変更が許可された在留資格の種類別では、通訳や情報処理などの仕事に携わる「技術・人文知識・国際業務」という資格が全体の９割以上を占めています。<br /><br />国籍や地域別では、中国が最も多く１万326人、次いでベトナムが4633人、ネパールが2026人などとなっています。<br /><br />就職する外国人留学生が過去最多を更新したことについて、法務省入国管理局は「就職を支援する環境整備が進む一方、ビジネスの国際化で企業側のニーズが増していることが背景にある」と分析しています。",
  "body": [
    {
      "title": "",
      "img": "",
      "align": "",
      "text": "",
      "textPos": ""
    }
  ],
  "relationNews": [
    {
      "link": "html/20181010/k10011665721000.html",
      "title": "新在留資格 強制退去者の引き取り拒否の国は除外検討",
      "date": "10月10日  12時42分",
      "datetime": "2018-10-10T12:42",
      "imgPath": "html/20181010/K10011665721_1810101229_1810101243_01_02.jpg",
      "iconPath": "html/20181010/K10011665721_1810101229_1810101243_02_01.jpg",
      "video": "",
      "duration": 0
    },
    {
      "link": "html/20181009/k10011664611000.html",
      "title": "働く人たちの景気実感 観光客減などで指数小幅に悪化",
      "date": "10月9日  15時56分",
      "datetime": "2018-10-09T15:56",
      "imgPath": "html/20181009/K10011664611_1810091551_1810091556_01_02.jpg",
      "iconPath": "html/20181009/K10011664611_1810091551_1810091556_02_01.jpg",
      "video": "",
      "duration": 0
    },
    {
      "link": "html/20181009/k10011663911000.html",
      "title": "逮捕リスク高い「受け子」に外国人勧誘増加 特殊詐欺",
      "date": "10月9日  4時07分",
      "datetime": "2018-10-09T04:07",
      "imgPath": "html/20181009/K10011663911_1810090504_1810090506_01_03.jpg",
      "iconPath": "html/20181009/K10011663911_1810090504_1810090506_02_01.jpg",
      "video": "https://www3.nhk.or.jp/news/html/20181009/movie/k10011663911_201810090504_201810090505.html",
      "duration": 87
    }
  ],
  "relationLink": [
    {
      "link": "https://www.nhk.or.jp/d-navi/izon/tokyo.html",
      "title": "外国人“依存”ニッポン",
      "time": "スペシャルコンテンツ",
      "datetime": ""
    }
  ],
  "word": [],
  "news_id": "k10011665771000",
  "yyyy": "2018",
  "mm": "10",
  "dd": "10",
  "url": "https://www3.nhk.or.jp/news/html/20181010/k10011665771000.html"
}